adjspecies.py
adjspecies/__init__.py
adjspecies/adjectives.txt
adjspecies/nouns.txt
adjspecies/species.txt
adjspecies-0.1.3.data/scripts/adjspecies
adjspecies-0.1.3.dist-info/DESCRIPTION.rst
adjspecies-0.1.3.dist-info/entry_points.txt
adjspecies-0.1.3.dist-info/METADATA
adjspecies-0.1.3.dist-info/pydist.json
adjspecies-0.1.3.dist-info/RECORD
adjspecies-0.1.3.dist-info/top_level.txt
adjspecies-0.1.3.dist-info/WHEEL
