Metadata-Version: 2.0
Name: adjspecies
Version: 0.1.3
Summary: 
